{"textures":[{"image":"84-0.webp","format":"RGBA8888","size":{"w":509,"h":1194},"scale":1,"frames":[{"filename":"penguin/84_1","rotated":false,"trimmed":true,"sourceSize":{"w":400,"h":400},"spriteSourceSize":{"x":162,"y":154,"w":76,"h":58},"frame":{"x":1,"y":1,"w":76,"h":58}},{"filename":"penguin/84_21","rotated":false,"trimmed":true,"sourceSize":{"w":400,"h":400},"spriteSourceSize":{"x":171,"y":154,"w":55,"h":58},"frame":{"x":79,"y":1,"w":55,"h":58}},{"filename":"penguin/84_22","rotated":false,"trimmed":true,"sourceSize":{"w":400,"h":400},"spriteSourceSize":{"x":172,"y":154,"w":55,"h":58},"frame":{"x":136,"y":1,"w":55,"h":58}},{"filename":"penguin/84_23","rotated":false,"trimmed":true,"sourceSize":{"w":400,"h":400},"spriteSourceSize":{"x":174,"y":154,"w":55,"h":58},"frame":{"x":193,"y":1,"w":55,"h":58}},{"filename":"penguin/84_4","rotated":false,"trimmed":true,"sourceSize":{"w":400,"h":400},"spriteSourceSize":{"x":150,"y":153,"w":94,"h":58},"frame":{"x":250,"y":1,"w":94,"h":58}},{"filename":"penguin/84_43","rotated":false,"trimmed":true,"sourceSize":{"w":400,"h":400},"spriteSourceSize":{"x":173,"y":154,"w":56,"h":58},"frame":{"x":346,"y":1,"w":56,"h":58}},{"filename":"penguin/84_44","rotated":false,"trimmed":true,"sourceSize":{"w":400,"h":400},"spriteSourceSize":{"x":172,"y":154,"w":55,"h":58},"frame":{"x":404,"y":1,"w":55,"h":58}},{"filename":"penguin/84_45","rotated":false,"trimmed":true,"sourceSize":{"w":400,"h":400},"spriteSourceSize":{"x":171,"y":154,"w":55,"h":58},"frame":{"x":1,"y":61,"w":55,"h":58}},{"filename":"penguin/84_2","rotated":false,"trimmed":true,"sourceSize":{"w":400,"h":400},"spriteSourceSize":{"x":160,"y":153,"w":79,"h":59},"frame":{"x":58,"y":61,"w":79,"h":59}},{"filename":"penguin/84_24","rotated":false,"trimmed":true,"sourceSize":{"w":400,"h":400},"spriteSourceSize":{"x":175,"y":153,"w":55,"h":59},"frame":{"x":139,"y":61,"w":55,"h":59}},{"filename":"penguin/84_25","rotated":false,"trimmed":true,"sourceSize":{"w":400,"h":400},"spriteSourceSize":{"x":178,"y":153,"w":53,"h":59},"frame":{"x":196,"y":61,"w":53,"h":59}},{"filename":"penguin/84_3","rotated":false,"trimmed":true,"sourceSize":{"w":400,"h":400},"spriteSourceSize":{"x":156,"y":153,"w":85,"h":59},"frame":{"x":251,"y":61,"w":85,"h":59}},{"filename":"penguin/84_46","rotated":false,"trimmed":true,"sourceSize":{"w":400,"h":400},"spriteSourceSize":{"x":170,"y":153,"w":55,"h":59},"frame":{"x":338,"y":61,"w":55,"h":59}},{"filename":"penguin/84_47","rotated":false,"trimmed":true,"sourceSize":{"w":400,"h":400},"spriteSourceSize":{"x":171,"y":153,"w":54,"h":59},"frame":{"x":395,"y":61,"w":54,"h":59}},{"filename":"penguin/84_20","rotated":false,"trimmed":true,"sourceSize":{"w":400,"h":400},"spriteSourceSize":{"x":170,"y":153,"w":55,"h":60},"frame":{"x":451,"y":61,"w":55,"h":60}},{"filename":"penguin/84_6","rotated":false,"trimmed":true,"sourceSize":{"w":400,"h":400},"spriteSourceSize":{"x":139,"y":153,"w":108,"h":59},"frame":{"x":1,"y":122,"w":108,"h":59}},{"filename":"penguin/84_26","rotated":false,"trimmed":true,"sourceSize":{"w":400,"h":400},"spriteSourceSize":{"x":173,"y":152,"w":60,"h":60},"frame":{"x":111,"y":122,"w":60,"h":60}},{"filename":"penguin/84_27","rotated":false,"trimmed":true,"sourceSize":{"w":400,"h":400},"spriteSourceSize":{"x":169,"y":152,"w":74,"h":60},"frame":{"x":173,"y":122,"w":74,"h":60}},{"filename":"penguin/84_28","rotated":false,"trimmed":true,"sourceSize":{"w":400,"h":400},"spriteSourceSize":{"x":166,"y":153,"w":84,"h":60},"frame":{"x":249,"y":122,"w":84,"h":60}},{"filename":"penguin/84_42","rotated":false,"trimmed":true,"sourceSize":{"w":400,"h":400},"spriteSourceSize":{"x":175,"y":153,"w":55,"h":60},"frame":{"x":335,"y":122,"w":55,"h":60}},{"filename":"penguin/84_7","rotated":false,"trimmed":true,"sourceSize":{"w":400,"h":400},"spriteSourceSize":{"x":164,"y":153,"w":56,"h":60},"frame":{"x":392,"y":122,"w":56,"h":60}},{"filename":"penguin/84_19","rotated":false,"trimmed":true,"sourceSize":{"w":400,"h":400},"spriteSourceSize":{"x":172,"y":152,"w":53,"h":61},"frame":{"x":450,"y":123,"w":53,"h":61}},{"filename":"penguin/84_48","rotated":false,"trimmed":true,"sourceSize":{"w":400,"h":400},"spriteSourceSize":{"x":166,"y":152,"w":64,"h":60},"frame":{"x":1,"y":183,"w":64,"h":60}},{"filename":"penguin/84_5","rotated":false,"trimmed":true,"sourceSize":{"w":400,"h":400},"spriteSourceSize":{"x":144,"y":152,"w":102,"h":60},"frame":{"x":67,"y":184,"w":102,"h":60}},{"filename":"penguin/84_29","rotated":false,"trimmed":true,"sourceSize":{"w":400,"h":400},"spriteSourceSize":{"x":159,"y":153,"w":103,"h":61},"frame":{"x":171,"y":184,"w":103,"h":61}},{"filename":"penguin/84_41","rotated":false,"trimmed":true,"sourceSize":{"w":400,"h":400},"spriteSourceSize":{"x":177,"y":152,"w":55,"h":61},"frame":{"x":276,"y":184,"w":55,"h":61}},{"filename":"penguin/84_49","rotated":false,"trimmed":true,"sourceSize":{"w":400,"h":400},"spriteSourceSize":{"x":158,"y":152,"w":77,"h":61},"frame":{"x":333,"y":184,"w":77,"h":61}},{"filename":"penguin/84_50","rotated":false,"trimmed":true,"sourceSize":{"w":400,"h":400},"spriteSourceSize":{"x":144,"y":153,"w":93,"h":61},"frame":{"x":412,"y":186,"w":93,"h":61}},{"filename":"penguin/84_8","rotated":false,"trimmed":true,"sourceSize":{"w":400,"h":400},"spriteSourceSize":{"x":162,"y":154,"w":56,"h":61},"frame":{"x":1,"y":245,"w":56,"h":61}},{"filename":"penguin/84_9","rotated":false,"trimmed":true,"sourceSize":{"w":400,"h":400},"spriteSourceSize":{"x":161,"y":155,"w":55,"h":61},"frame":{"x":59,"y":246,"w":55,"h":61}},{"filename":"penguin/84_10","rotated":false,"trimmed":true,"sourceSize":{"w":400,"h":400},"spriteSourceSize":{"x":160,"y":156,"w":55,"h":62},"frame":{"x":116,"y":247,"w":55,"h":62}},{"filename":"penguin/84_11","rotated":false,"trimmed":true,"sourceSize":{"w":400,"h":400},"spriteSourceSize":{"x":160,"y":156,"w":54,"h":62},"frame":{"x":173,"y":247,"w":54,"h":62}},{"filename":"penguin/84_18","rotated":false,"trimmed":true,"sourceSize":{"w":400,"h":400},"spriteSourceSize":{"x":165,"y":151,"w":66,"h":62},"frame":{"x":229,"y":247,"w":66,"h":62}},{"filename":"penguin/84_30","rotated":false,"trimmed":true,"sourceSize":{"w":400,"h":400},"spriteSourceSize":{"x":183,"y":154,"w":86,"h":62},"frame":{"x":297,"y":247,"w":86,"h":62}},{"filename":"penguin/84_31","rotated":false,"trimmed":true,"sourceSize":{"w":400,"h":400},"spriteSourceSize":{"x":184,"y":155,"w":55,"h":62},"frame":{"x":385,"y":249,"w":55,"h":62}},{"filename":"penguin/84_32","rotated":false,"trimmed":true,"sourceSize":{"w":400,"h":400},"spriteSourceSize":{"x":185,"y":156,"w":54,"h":62},"frame":{"x":442,"y":249,"w":54,"h":62}},{"filename":"penguin/84_33","rotated":false,"trimmed":true,"sourceSize":{"w":400,"h":400},"spriteSourceSize":{"x":185,"y":156,"w":55,"h":62},"frame":{"x":1,"y":308,"w":55,"h":62}},{"filename":"penguin/84_52","rotated":false,"trimmed":true,"sourceSize":{"w":400,"h":400},"spriteSourceSize":{"x":162,"y":154,"w":55,"h":62},"frame":{"x":58,"y":309,"w":55,"h":62}},{"filename":"penguin/84_51","rotated":false,"trimmed":true,"sourceSize":{"w":400,"h":400},"spriteSourceSize":{"x":163,"y":153,"w":79,"h":62},"frame":{"x":115,"y":311,"w":79,"h":62}},{"filename":"penguin/84_53","rotated":false,"trimmed":true,"sourceSize":{"w":400,"h":400},"spriteSourceSize":{"x":161,"y":155,"w":54,"h":62},"frame":{"x":196,"y":311,"w":54,"h":62}},{"filename":"penguin/84_54","rotated":false,"trimmed":true,"sourceSize":{"w":400,"h":400},"spriteSourceSize":{"x":160,"y":156,"w":55,"h":62},"frame":{"x":252,"y":311,"w":55,"h":62}},{"filename":"penguin/84_55","rotated":false,"trimmed":true,"sourceSize":{"w":400,"h":400},"spriteSourceSize":{"x":160,"y":156,"w":54,"h":62},"frame":{"x":309,"y":311,"w":54,"h":62}},{"filename":"body/84_12","rotated":false,"trimmed":true,"sourceSize":{"w":400,"h":400},"spriteSourceSize":{"x":126,"y":141,"w":123,"h":63},"frame":{"x":365,"y":313,"w":123,"h":63}},{"filename":"penguin/84_12","rotated":false,"trimmed":true,"sourceSize":{"w":400,"h":400},"spriteSourceSize":{"x":160,"y":155,"w":55,"h":63},"frame":{"x":1,"y":372,"w":55,"h":63}},{"filename":"penguin/84_34","rotated":false,"trimmed":true,"sourceSize":{"w":400,"h":400},"spriteSourceSize":{"x":185,"y":155,"w":55,"h":63},"frame":{"x":58,"y":373,"w":55,"h":63}},{"filename":"body/84_31","rotated":false,"trimmed":true,"sourceSize":{"w":400,"h":400},"spriteSourceSize":{"x":153,"y":141,"w":119,"h":63},"frame":{"x":115,"y":375,"w":119,"h":63}},{"filename":"penguin/84_13","rotated":false,"trimmed":true,"sourceSize":{"w":400,"h":400},"spriteSourceSize":{"x":160,"y":154,"w":56,"h":63},"frame":{"x":236,"y":375,"w":56,"h":63}},{"filename":"penguin/84_56","rotated":false,"trimmed":true,"sourceSize":{"w":400,"h":400},"spriteSourceSize":{"x":160,"y":154,"w":56,"h":63},"frame":{"x":236,"y":375,"w":56,"h":63}},{"filename":"penguin/84_35","rotated":false,"trimmed":true,"sourceSize":{"w":400,"h":400},"spriteSourceSize":{"x":184,"y":154,"w":55,"h":63},"frame":{"x":294,"y":375,"w":55,"h":63}},{"filename":"penguin/84_17","rotated":false,"trimmed":true,"sourceSize":{"w":400,"h":400},"spriteSourceSize":{"x":157,"y":150,"w":77,"h":63},"frame":{"x":351,"y":378,"w":77,"h":63}},{"filename":"penguin/84_40","rotated":false,"trimmed":true,"sourceSize":{"w":400,"h":400},"spriteSourceSize":{"x":173,"y":150,"w":60,"h":63},"frame":{"x":430,"y":378,"w":60,"h":63}},{"filename":"penguin/84_14","rotated":false,"trimmed":true,"sourceSize":{"w":400,"h":400},"spriteSourceSize":{"x":161,"y":152,"w":56,"h":64},"frame":{"x":1,"y":438,"w":56,"h":64}},{"filename":"body/84_10","rotated":false,"trimmed":true,"sourceSize":{"w":400,"h":400},"spriteSourceSize":{"x":125,"y":141,"w":125,"h":64},"frame":{"x":59,"y":440,"w":125,"h":64}},{"filename":"body/84_11","rotated":false,"trimmed":true,"sourceSize":{"w":400,"h":400},"spriteSourceSize":{"x":125,"y":141,"w":124,"h":64},"frame":{"x":186,"y":440,"w":124,"h":64}},{"filename":"body/84_55","rotated":false,"trimmed":true,"sourceSize":{"w":400,"h":400},"spriteSourceSize":{"x":125,"y":141,"w":124,"h":64},"frame":{"x":186,"y":440,"w":124,"h":64}},{"filename":"body/84_54","rotated":false,"trimmed":true,"sourceSize":{"w":400,"h":400},"spriteSourceSize":{"x":126,"y":141,"w":123,"h":64},"frame":{"x":312,"y":443,"w":123,"h":64}},{"filename":"penguin/84_39","rotated":false,"trimmed":true,"sourceSize":{"w":400,"h":400},"spriteSourceSize":{"x":169,"y":150,"w":71,"h":64},"frame":{"x":437,"y":443,"w":71,"h":64}},{"filename":"body/84_23","rotated":false,"trimmed":true,"sourceSize":{"w":400,"h":400},"spriteSourceSize":{"x":174,"y":139,"w":55,"h":65},"frame":{"x":1,"y":504,"w":55,"h":65}},{"filename":"body/84_9","rotated":false,"trimmed":true,"sourceSize":{"w":400,"h":400},"spriteSourceSize":{"x":126,"y":140,"w":125,"h":64},"frame":{"x":58,"y":506,"w":125,"h":64}},{"filename":"penguin/84_36","rotated":false,"trimmed":true,"sourceSize":{"w":400,"h":400},"spriteSourceSize":{"x":183,"y":152,"w":75,"h":64},"frame":{"x":185,"y":506,"w":75,"h":64}},{"filename":"body/84_43","rotated":false,"trimmed":true,"sourceSize":{"w":400,"h":400},"spriteSourceSize":{"x":174,"y":139,"w":55,"h":65},"frame":{"x":262,"y":509,"w":55,"h":65}},{"filename":"body/84_1","rotated":false,"trimmed":true,"sourceSize":{"w":400,"h":400},"spriteSourceSize":{"x":161,"y":139,"w":78,"h":65},"frame":{"x":319,"y":509,"w":78,"h":65}},{"filename":"body/84_45","rotated":false,"trimmed":true,"sourceSize":{"w":400,"h":400},"spriteSourceSize":{"x":171,"y":139,"w":56,"h":65},"frame":{"x":399,"y":509,"w":56,"h":65}},{"filename":"body/84_13","rotated":false,"trimmed":true,"sourceSize":{"w":400,"h":400},"spriteSourceSize":{"x":128,"y":139,"w":119,"h":65},"frame":{"x":1,"y":572,"w":119,"h":65}},{"filename":"body/84_56","rotated":false,"trimmed":true,"sourceSize":{"w":400,"h":400},"spriteSourceSize":{"x":128,"y":139,"w":119,"h":65},"frame":{"x":1,"y":572,"w":119,"h":65}},{"filename":"body/84_28","rotated":false,"trimmed":true,"sourceSize":{"w":400,"h":400},"spriteSourceSize":{"x":161,"y":138,"w":91,"h":65},"frame":{"x":122,"y":572,"w":91,"h":65}},{"filename":"body/84_29","rotated":false,"trimmed":true,"sourceSize":{"w":400,"h":400},"spriteSourceSize":{"x":158,"y":139,"w":106,"h":65},"frame":{"x":215,"y":576,"w":106,"h":65}},{"filename":"body/84_30","rotated":false,"trimmed":true,"sourceSize":{"w":400,"h":400},"spriteSourceSize":{"x":155,"y":139,"w":115,"h":65},"frame":{"x":323,"y":576,"w":115,"h":65}},{"filename":"body/84_20","rotated":false,"trimmed":true,"sourceSize":{"w":400,"h":400},"spriteSourceSize":{"x":170,"y":138,"w":56,"h":66},"frame":{"x":440,"y":576,"w":56,"h":66}},{"filename":"body/84_32","rotated":false,"trimmed":true,"sourceSize":{"w":400,"h":400},"spriteSourceSize":{"x":153,"y":140,"w":120,"h":65},"frame":{"x":1,"y":639,"w":120,"h":65}},{"filename":"penguin/84_38","rotated":false,"trimmed":true,"sourceSize":{"w":400,"h":400},"spriteSourceSize":{"x":165,"y":149,"w":86,"h":65},"frame":{"x":123,"y":639,"w":86,"h":65}},{"filename":"body/84_33","rotated":false,"trimmed":true,"sourceSize":{"w":400,"h":400},"spriteSourceSize":{"x":152,"y":140,"w":122,"h":65},"frame":{"x":211,"y":643,"w":122,"h":65}},{"filename":"body/84_50","rotated":false,"trimmed":true,"sourceSize":{"w":400,"h":400},"spriteSourceSize":{"x":142,"y":138,"w":99,"h":65},"frame":{"x":335,"y":643,"w":99,"h":65}},{"filename":"body/84_21","rotated":false,"trimmed":true,"sourceSize":{"w":400,"h":400},"spriteSourceSize":{"x":171,"y":138,"w":56,"h":66},"frame":{"x":436,"y":644,"w":56,"h":66}},{"filename":"body/84_35","rotated":false,"trimmed":true,"sourceSize":{"w":400,"h":400},"spriteSourceSize":{"x":153,"y":139,"w":120,"h":65},"frame":{"x":1,"y":706,"w":120,"h":65}},{"filename":"body/84_2","rotated":false,"trimmed":true,"sourceSize":{"w":400,"h":400},"spriteSourceSize":{"x":160,"y":138,"w":80,"h":66},"frame":{"x":123,"y":706,"w":80,"h":66}},{"filename":"penguin/84_15","rotated":false,"trimmed":true,"sourceSize":{"w":400,"h":400},"spriteSourceSize":{"x":143,"y":150,"w":99,"h":65},"frame":{"x":205,"y":710,"w":99,"h":65}},{"filename":"body/84_52","rotated":false,"trimmed":true,"sourceSize":{"w":400,"h":400},"spriteSourceSize":{"x":131,"y":139,"w":114,"h":65},"frame":{"x":306,"y":710,"w":114,"h":65}},{"filename":"body/84_22","rotated":false,"trimmed":true,"sourceSize":{"w":400,"h":400},"spriteSourceSize":{"x":172,"y":139,"w":56,"h":66},"frame":{"x":422,"y":712,"w":56,"h":66}},{"filename":"body/84_44","rotated":false,"trimmed":true,"sourceSize":{"w":400,"h":400},"spriteSourceSize":{"x":172,"y":139,"w":56,"h":66},"frame":{"x":422,"y":712,"w":56,"h":66}},{"filename":"body/84_53","rotated":false,"trimmed":true,"sourceSize":{"w":400,"h":400},"spriteSourceSize":{"x":128,"y":140,"w":119,"h":65},"frame":{"x":1,"y":773,"w":119,"h":65}},{"filename":"body/84_24","rotated":false,"trimmed":true,"sourceSize":{"w":400,"h":400},"spriteSourceSize":{"x":175,"y":138,"w":55,"h":66},"frame":{"x":122,"y":774,"w":55,"h":66}},{"filename":"body/84_7","rotated":false,"trimmed":true,"sourceSize":{"w":400,"h":400},"spriteSourceSize":{"x":131,"y":138,"w":120,"h":65},"frame":{"x":179,"y":777,"w":120,"h":65}},{"filename":"penguin/84_16","rotated":false,"trimmed":true,"sourceSize":{"w":400,"h":400},"spriteSourceSize":{"x":143,"y":149,"w":94,"h":65},"frame":{"x":301,"y":777,"w":94,"h":65}},{"filename":"penguin/84_37","rotated":false,"trimmed":true,"sourceSize":{"w":400,"h":400},"spriteSourceSize":{"x":159,"y":150,"w":104,"h":65},"frame":{"x":397,"y":780,"w":104,"h":65}},{"filename":"body/84_14","rotated":false,"trimmed":true,"sourceSize":{"w":400,"h":400},"spriteSourceSize":{"x":130,"y":137,"w":115,"h":66},"frame":{"x":1,"y":840,"w":115,"h":66}},{"filename":"body/84_42","rotated":false,"trimmed":true,"sourceSize":{"w":400,"h":400},"spriteSourceSize":{"x":175,"y":138,"w":55,"h":66},"frame":{"x":118,"y":842,"w":55,"h":66}},{"filename":"body/84_8","rotated":false,"trimmed":true,"sourceSize":{"w":400,"h":400},"spriteSourceSize":{"x":128,"y":139,"w":123,"h":65},"frame":{"x":175,"y":844,"w":123,"h":65}},{"filename":"body/84_3","rotated":false,"trimmed":true,"sourceSize":{"w":400,"h":400},"spriteSourceSize":{"x":155,"y":138,"w":87,"h":66},"frame":{"x":300,"y":844,"w":87,"h":66}},{"filename":"body/84_36","rotated":false,"trimmed":true,"sourceSize":{"w":400,"h":400},"spriteSourceSize":{"x":154,"y":137,"w":117,"h":66},"frame":{"x":389,"y":847,"w":117,"h":66}},{"filename":"body/84_46","rotated":false,"trimmed":true,"sourceSize":{"w":400,"h":400},"spriteSourceSize":{"x":170,"y":138,"w":56,"h":66},"frame":{"x":1,"y":908,"w":56,"h":66}},{"filename":"body/84_49","rotated":false,"trimmed":true,"sourceSize":{"w":400,"h":400},"spriteSourceSize":{"x":152,"y":137,"w":88,"h":66},"frame":{"x":59,"y":910,"w":88,"h":66}},{"filename":"body/84_34","rotated":false,"trimmed":true,"sourceSize":{"w":400,"h":400},"spriteSourceSize":{"x":152,"y":139,"w":121,"h":66},"frame":{"x":149,"y":911,"w":121,"h":66}},{"filename":"body/84_5","rotated":false,"trimmed":true,"sourceSize":{"w":400,"h":400},"spriteSourceSize":{"x":143,"y":137,"w":105,"h":66},"frame":{"x":272,"y":912,"w":105,"h":66}},{"filename":"body/84_51","rotated":false,"trimmed":true,"sourceSize":{"w":400,"h":400},"spriteSourceSize":{"x":134,"y":138,"w":109,"h":66},"frame":{"x":379,"y":915,"w":109,"h":66}},{"filename":"body/84_6","rotated":false,"trimmed":true,"sourceSize":{"w":400,"h":400},"spriteSourceSize":{"x":136,"y":137,"w":114,"h":66},"frame":{"x":1,"y":978,"w":114,"h":66}},{"filename":"body/84_15","rotated":false,"trimmed":true,"sourceSize":{"w":400,"h":400},"spriteSourceSize":{"x":133,"y":135,"w":110,"h":67},"frame":{"x":117,"y":979,"w":110,"h":67}},{"filename":"body/84_27","rotated":false,"trimmed":true,"sourceSize":{"w":400,"h":400},"spriteSourceSize":{"x":164,"y":137,"w":82,"h":67},"frame":{"x":229,"y":980,"w":82,"h":67}},{"filename":"body/84_25","rotated":false,"trimmed":true,"sourceSize":{"w":400,"h":400},"spriteSourceSize":{"x":173,"y":138,"w":60,"h":68},"frame":{"x":313,"y":980,"w":60,"h":68}},{"filename":"body/84_37","rotated":false,"trimmed":true,"sourceSize":{"w":400,"h":400},"spriteSourceSize":{"x":157,"y":135,"w":108,"h":67},"frame":{"x":375,"y":983,"w":108,"h":67}},{"filename":"body/84_4","rotated":false,"trimmed":true,"sourceSize":{"w":400,"h":400},"spriteSourceSize":{"x":149,"y":137,"w":96,"h":67},"frame":{"x":1,"y":1046,"w":96,"h":67}},{"filename":"body/84_17","rotated":false,"trimmed":true,"sourceSize":{"w":400,"h":400},"spriteSourceSize":{"x":151,"y":134,"w":89,"h":68},"frame":{"x":99,"y":1048,"w":89,"h":68}},{"filename":"body/84_38","rotated":false,"trimmed":true,"sourceSize":{"w":400,"h":400},"spriteSourceSize":{"x":161,"y":134,"w":92,"h":68},"frame":{"x":190,"y":1049,"w":92,"h":68}},{"filename":"body/84_39","rotated":false,"trimmed":true,"sourceSize":{"w":400,"h":400},"spriteSourceSize":{"x":163,"y":134,"w":84,"h":68},"frame":{"x":284,"y":1050,"w":84,"h":68}},{"filename":"body/84_16","rotated":false,"trimmed":true,"sourceSize":{"w":400,"h":400},"spriteSourceSize":{"x":141,"y":134,"w":101,"h":68},"frame":{"x":370,"y":1052,"w":101,"h":68}},{"filename":"body/84_47","rotated":false,"trimmed":true,"sourceSize":{"w":400,"h":400},"spriteSourceSize":{"x":166,"y":138,"w":64,"h":68},"frame":{"x":1,"y":1115,"w":64,"h":68}},{"filename":"body/84_19","rotated":false,"trimmed":true,"sourceSize":{"w":400,"h":400},"spriteSourceSize":{"x":165,"y":137,"w":65,"h":69},"frame":{"x":67,"y":1118,"w":65,"h":69}},{"filename":"body/84_41","rotated":false,"trimmed":true,"sourceSize":{"w":400,"h":400},"spriteSourceSize":{"x":173,"y":136,"w":60,"h":69},"frame":{"x":134,"y":1119,"w":60,"h":69}},{"filename":"body/84_48","rotated":false,"trimmed":true,"sourceSize":{"w":400,"h":400},"spriteSourceSize":{"x":158,"y":137,"w":78,"h":69},"frame":{"x":196,"y":1119,"w":78,"h":69}},{"filename":"body/84_18","rotated":false,"trimmed":true,"sourceSize":{"w":400,"h":400},"spriteSourceSize":{"x":158,"y":135,"w":78,"h":70},"frame":{"x":276,"y":1120,"w":78,"h":70}},{"filename":"body/84_26","rotated":false,"trimmed":true,"sourceSize":{"w":400,"h":400},"spriteSourceSize":{"x":168,"y":137,"w":72,"h":70},"frame":{"x":356,"y":1122,"w":72,"h":70}},{"filename":"body/84_40","rotated":false,"trimmed":true,"sourceSize":{"w":400,"h":400},"spriteSourceSize":{"x":168,"y":135,"w":73,"h":71},"frame":{"x":430,"y":1122,"w":73,"h":71}}]}],"meta":{"app":"https://www.codeandweb.com/texturepacker","version":"3.0","smartupdate":"$TexturePacker:SmartUpdate:f38101456651a1d7f3c275d180481642:324402ee90bac00ebf9607b26dc223f2:96940f5a9336ee97e30675ad3ca65da0$"}}